{
  "project_info": {
    "project_number": "30299998370",
    "project_id": "busawaylogin",
    "storage_bucket": "busawaylogin.appspot.com"
  },
  "client": [
    {
      "client_info": {
        "mobilesdk_app_id": "1:30299998370:android:c5b46fa32f1ecf07cbaffb",
        "android_client_info": {
          "package_name": "com.example.bus_app"
        }
      },
      "oauth_client": [
        {
          "client_id": "30299998370-g38ncrq9rpl2u5fi8vhq772rqsbakdj7.apps.googleusercontent.com",
          "client_type": 3
        }
      ],
      "api_key": [
        {
          "current_key": "AIzaSyA4pNs59mkjzpRPaXaIxz9b8inAlyGpJ7w"
        }
      ],
      "services": {
        "appinvite_service": {
          "other_platform_oauth_client": [
            {
              "client_id": "30299998370-g38ncrq9rpl2u5fi8vhq772rqsbakdj7.apps.googleusercontent.com",
              "client_type": 3
            }
          ]
        }
      }
    }
  ],
  "configuration_version": "1"
}